dp_utils/__init__.py
dp_utils/dp_logging.py
tests/__init__.py
tests/test_dp_logging.py
digiprospector_utils-1.0.0.dist-info/LICENSE
digiprospector_utils-1.0.0.dist-info/METADATA
digiprospector_utils-1.0.0.dist-info/WHEEL
digiprospector_utils-1.0.0.dist-info/top_level.txt
digiprospector_utils-1.0.0.dist-info/RECORD
